mindlab/__init__.py
mindlab/lab.py
mindlab/magics.py
mindlab/mock_data.py
mindlab/plot.py
mindlab/py.typed
mindlab/utils.py
mindlab/config/ipython_kernel_config.py
mindlab/config/jupyterlab_settings_overrides.json
mindlab/fonts/Lato-Bold.ttf
mindlab/fonts/Lato-BoldItalic.ttf
mindlab/fonts/Lato-Italic.ttf
mindlab/fonts/Lato-LICENSE.txt
mindlab/fonts/Lato-README.txt
mindlab/fonts/Lato-Regular.ttf
mindlab/styles/__init__.py
mindlab/styles/logikal.mplstyle
mindlab/styles/logikal_dark.mplstyle
mindlab/styles/logikal_docs.mplstyle
mindlab/styles/logikal_light.mplstyle
mindlab/styles/logikal_slides.mplstyle
mindlab/styles/mindlab.mplstyle
mindlab/styles/mindlab_dark.mplstyle
mindlab/styles/mindlab_light.mplstyle
mindlab-3.0.0.dist-info/licenses/LICENSE.txt
mindlab-3.0.0.dist-info/METADATA
mindlab-3.0.0.dist-info/WHEEL
mindlab-3.0.0.dist-info/entry_points.txt
mindlab-3.0.0.dist-info/top_level.txt
mindlab-3.0.0.dist-info/RECORD
